{
    "content": [{
        "img": "img/k1.jpg",
        "title": "SCiO微型光谱仪",
        "price": "￥1212",
        "like": 3,
        "comment": 3,
        "like_img": "img/xin.png",
        "comment_img": "img/reply.png",
        "txt": "可以测试食物成分及营养"
    }, {
        "img": "img/k2.jpg",
        "title": "B&O SengSound 35 音响",
        "price": "￥512",
        "like": 3,
        "comment": 3,
        "like_img": "img/xin.png",
        "comment_img": "img/reply.png",
        "txt": "支持所有音乐流媒体服务"
    }, {
        "img": "img/k3.jpg",
        "title": "Mozbil 触控吸色笔",
        "price": "￥暂无",
        "like": 3,
        "comment": 3,
        "like_img": "img/xin.png",
        "comment_img": "img/reply.png",
        "txt": "能吸收650000种颜色"
    }, {
        "img": "img/k4.jpg",
        "title": "XPlORER 2航拍飞行器",
        "price": "￥433",
        "like": 3,
        "comment": 3,
        "like_img": "img/xin.png",
        "comment_img": "img/reply.png",
        "txt": "搭载自动避障系统"
    }, {
        "img": "img/k1.jpg",
        "title": "SCiO微型光谱仪",
        "price": "￥1212",
        "like": 3,
        "comment": 3,
        "like_img": "img/xin.png",
        "comment_img": "img/reply.png",
        "txt": "可以测试食物成分及营养"
    }, {
        "img": "img/k2.jpg",
        "title": "B&O SengSound 35 音响",
        "price": "￥512",
        "like": 3,
        "comment": 3,
        "like_img": "img/xin.png",
        "comment_img": "img/reply.png",
        "txt": "支持所有音乐流媒体服务"
    }, {
        "img": "img/k3.jpg",
        "title": "Mozbil 触控吸色笔",
        "price": "￥暂无",
        "like": 3,
        "comment": 3,
        "like_img": "img/xin.png",
        "comment_img": "img/reply.png",
        "txt": "能吸收650000种颜色"
    }, {
        "img": "img/k4.jpg",
        "title": "XPlORER 2航拍飞行器",
        "price": "￥433",
        "like": 3,
        "comment": 3,
        "like_img": "img/xin.png",
        "comment_img": "img/reply.png",
        "txt": "搭载自动避障系统"
    }, {
        "img": "img/k1.jpg",
        "title": "SCiO微型光谱仪",
        "price": "￥1212",
        "like": 3,
        "comment": 3,
        "like_img": "img/xin.png",
        "comment_img": "img/reply.png",
        "txt": "可以测试食物成分及营养"
    }, {
        "img": "img/k2.jpg",
        "title": "B&O SengSound 35 音响",
        "price": "￥512",
        "like": 3,
        "comment": 3,
        "like_img": "img/xin.png",
        "comment_img": "img/reply.png",
        "txt": "支持所有音乐流媒体服务"
    }, {
        "img": "img/k3.jpg",
        "title": "Mozbil 触控吸色笔",
        "price": "￥暂无",
        "like": 3,
        "comment": 3,
        "like_img": "img/xin.png",
        "comment_img": "img/reply.png",
        "txt": "能吸收650000种颜色"
    }, {
        "img": "img/k4.jpg",
        "title": "XPlORER 2航拍飞行器",
        "price": "￥433",
        "like": 3,
        "comment": 3,
        "like_img": "img/xin.png",
        "comment_img": "img/reply.png",
        "txt": "搭载自动避障系统"
    }, {
        "img": "img/k1.jpg",
        "title": "SCiO微型光谱仪",
        "price": "￥1212",
        "like": 3,
        "comment": 3,
        "like_img": "img/xin.png",
        "comment_img": "img/reply.png",
        "txt": "可以测试食物成分及营养"
    }, {
        "img": "img/k2.jpg",
        "title": "B&O SengSound 35 音响",
        "price": "￥512",
        "like": 3,
        "comment": 3,
        "like_img": "img/xin.png",
        "comment_img": "img/reply.png",
        "txt": "支持所有音乐流媒体服务"
    }, {
        "img": "img/k3.jpg",
        "title": "Mozbil 触控吸色笔",
        "price": "￥暂无",
        "like": 3,
        "comment": 3,
        "like_img": "img/xin.png",
        "comment_img": "img/reply.png",
        "txt": "能吸收650000种颜色"
    }, {
        "img": "img/k4.jpg",
        "title": "XPlORER 2航拍飞行器",
        "price": "￥433",
        "like": 3,
        "comment": 3,
        "like_img": "img/xin.png",
        "comment_img": "img/reply.png",
        "txt": "搭载自动避障系统"
    }]
}